core_devoops/__init__.py
core_devoops/app_activity.py
core_devoops/app_rights.py
core_devoops/app_user.py
core_devoops/auth_configuration.py
core_devoops/authentication.py
core_devoops/check_dependencies.py
core_devoops/custom_equal.py
core_devoops/db_connection.py
core_devoops/db_filters.py
core_devoops/db_insertion.py
core_devoops/db_retrieval.py
core_devoops/enum_utils.py
core_devoops/list_utils.py
core_devoops/logger.py
core_devoops/pandas_utils.py
core_devoops/permissions.py
core_devoops/pydantic_utils.py
core_devoops/read_write.py
core_devoops/safe_utils.py
core_devoops-0.0.54.dist-info/LICENSE.md
core_devoops-0.0.54.dist-info/METADATA
core_devoops-0.0.54.dist-info/WHEEL
core_devoops-0.0.54.dist-info/RECORD
